rlfw/__init__.py
rlfw/loss.py
rlfw/network.py
rlfw/parameter.py
rlfw/util.py
rlfw/continuous/__init__.py
rlfw/continuous/algorithm.py
rlfw/continuous/policy.py
rlfw/continuous/value.py
rlfw/discrete/__init__.py
rlfw/discrete/algorithm.py
rlfw/discrete/policy.py
rlfw/discrete/value.py
rlfw-0.0.0.dist-info/LICENSE
rlfw-0.0.0.dist-info/METADATA
rlfw-0.0.0.dist-info/WHEEL
rlfw-0.0.0.dist-info/top_level.txt
rlfw-0.0.0.dist-info/RECORD
